{"cameraMode":{"drawMode":0,"name":"Shaded","section":"Shading Mode"},"sceneLighting":false,"audioPlay":false,"sceneViewState":{"showFog":true,"showMaterialUpdate":false,"showSkybox":false,"showFlares":true,"showImageEffects":true,"showParticleSystems":true},"in2DMode":false,"pivot":{"x":-0.7126966714859009,"y":-0.038600414991378787,"z":0.23134231567382813},"rotation":{"x":-0.18686018884181977,"y":0.32073450088500979,"z":-0.06276778876781464,"w":-0.9269782900810242},"size":2.7156667709350588,"orthographic":false}